square_auth/__init__.py
square_auth/auth.py
square_auth/client_credentials.py
square_auth/keycloak_client.py
square_auth/utils.py
square_auth-0.0.14.dist-info/LICENSE.txt
square_auth-0.0.14.dist-info/METADATA
square_auth-0.0.14.dist-info/WHEEL
square_auth-0.0.14.dist-info/entry_points.txt
square_auth-0.0.14.dist-info/top_level.txt
square_auth-0.0.14.dist-info/RECORD
